dactim_mri/__init__.py
dactim_mri/anonymization.py
dactim_mri/brain_extraction.py
dactim_mri/computation.py
dactim_mri/conversion.py
dactim_mri/data.py
dactim_mri/old.py
dactim_mri/sorting.py
dactim_mri/spectroscopy.py
dactim_mri/transformation.py
dactim_mri/utils.py
dactim_mri/visualization.py
dactim_mri-0.0.19.dist-info/METADATA
dactim_mri-0.0.19.dist-info/WHEEL
dactim_mri-0.0.19.dist-info/licenses/LICENSE
dactim_mri-0.0.19.dist-info/RECORD
