Metadata-Version: 2.1
Name: dactim_mri
Version: 0.0.19
Summary: A tool to preprocess MRI data
Author-email: Pierre FAYOLLE <pierre.fayolle@chu-poitiers.fr>
License-File: LICENSE
Requires-Python: >=3.7
